openalpr/__init__.py
openalpr/openalpr.py
openalpr-1.1.0.dist-info/LICENSE.txt
openalpr-1.1.0.dist-info/METADATA
openalpr-1.1.0.dist-info/WHEEL
openalpr-1.1.0.dist-info/top_level.txt
openalpr-1.1.0.dist-info/RECORD
